AUTHORS.rst
CONTRIBUTING.rst
HISTORY.rst
LICENSE
MANIFEST.in
README.rst
setup.py
underwear/__init__.py
underwear/bootstrap-ssh-keys.yml
underwear/django-stack.yml
underwear/run_underwear.py
underwear.egg-info/PKG-INFO
underwear.egg-info/SOURCES.txt
underwear.egg-info/dependency_links.txt
underwear.egg-info/not-zip-safe
underwear.egg-info/requires.txt
underwear.egg-info/top_level.txt
underwear/deploy/underwear.yml
underwear/group_vars/all
underwear/group_vars/dbservers
underwear/group_vars/webservers
underwear/management/__init__.py
underwear/management/commands/__init__.py
underwear/management/commands/deploy.py
underwear/roles/common/handlers/main.yml
underwear/roles/common/tasks/main.yml
underwear/roles/db/handlers/main.yml
underwear/roles/db/tasks/config_mysql.yml
underwear/roles/db/tasks/config_postgresql.yml
underwear/roles/db/tasks/install_db_packages.yml
underwear/roles/db/tasks/main.yml
underwear/roles/db/templates/pg_hba.conf.j2
underwear/roles/db/templates/postgresql.conf.j2
underwear/roles/upload_keys/tasks/create_deployer_user.yml
underwear/roles/upload_keys/tasks/main.yml
underwear/roles/web/handlers/main.yml
underwear/roles/web/tasks/config_supervisor.yml
underwear/roles/web/tasks/config_web_app.yml
underwear/roles/web/tasks/config_web_server.yml
underwear/roles/web/tasks/install_web_packages.yml
underwear/roles/web/tasks/main.yml
underwear/roles/web/templates/nginx_no_ssl.conf.j2
underwear/roles/web/templates/nginx_ssl.conf.j2
underwear/roles/web/templates/supervisor.conf.j2
underwear/roles/web/templates/supervisor.newrelic.conf.j2
underwear/ssh_conf/known_hosts