Metadata-Version: 1.1
Name: underwear
Version: 0.4.5
Summary: Dead simple LAMP-stack deployments for Python-powered web applications
Home-page: https://github.com/makaimc/underwear
Author: Matt Makai
Author-email: matthew.makai@gmail.com
License: MIT
Keywords: underwear,deployment,django,LAMP,WSGI,ansible
Platform: UNKNOWN
Classifier: Development Status :: 4 - Beta
Classifier: Intended Audience :: Developers
Classifier: License :: OSI Approved :: MIT License
Classifier: Natural Language :: English
Classifier: Programming Language :: Python :: 2
Classifier: Programming Language :: Python :: 2.6
Classifier: Programming Language :: Python :: 2.7
